alibabacloud_gateway_sls_util/__init__.py
alibabacloud_gateway_sls_util/client.py
alibabacloud_gateway_sls_util/log_group_serializer.py
alibabacloud_gateway_sls_util-0.4.0.dist-info/METADATA
alibabacloud_gateway_sls_util-0.4.0.dist-info/WHEEL
alibabacloud_gateway_sls_util-0.4.0.dist-info/top_level.txt
alibabacloud_gateway_sls_util-0.4.0.dist-info/RECORD
